chorderizer/__init__.py
chorderizer/chorderizer.py
chorderizer-0.1.1.dist-info/licenses/LICENSE.md
chorderizer-0.1.1.dist-info/METADATA
chorderizer-0.1.1.dist-info/WHEEL
chorderizer-0.1.1.dist-info/entry_points.txt
chorderizer-0.1.1.dist-info/top_level.txt
chorderizer-0.1.1.dist-info/RECORD
